{
	"values": [
		{
			"key": "minecraft:desert",
			"name": "DESERT",
			"ordinal": 4
		},
		{
			"key": "minecraft:jungle",
			"name": "JUNGLE",
			"ordinal": 2
		},
		{
			"key": "minecraft:plains",
			"name": "PLAINS",
			"ordinal": 1
		},
		{
			"key": "minecraft:savanna",
			"name": "SAVANNA",
			"ordinal": 5
		},
		{
			"key": "minecraft:snow",
			"name": "SNOW",
			"ordinal": 0
		},
		{
			"key": "minecraft:swamp",
			"name": "SWAMP",
			"ordinal": 6
		},
		{
			"key": "minecraft:taiga",
			"name": "TAIGA",
			"ordinal": 3
		}
	]
}
